{"boundaries": {"type": "FeatureCollection", "features": []}, "buildings": {"type": "FeatureCollection", "features": []}, "landuse_labels": {"type": "FeatureCollection", "features": []}, "places": {"type": "FeatureCollection", "features": []}, "transit": {"type": "FeatureCollection", "features": []}, "pois": {"type": "FeatureCollection", "features": [{"geometry": {"type": "Point", "coordinates": [87.79279, 23.47026]}, "type": "Feature", "properties": {"id": 794141583, "kind": "aerodrome", "min_zoom": 13.0, "name": "Guskhara Airfield"}}]}, "water": {"type": "FeatureCollection", "features": []}, "roads": {"type": "FeatureCollection", "features": [{"geometry": {"type": "LineString", "coordinates": [[87.76209, 23.44309], [87.76029, 23.44947], [87.75879, 23.45363]]}, "type": "Feature", "properties": {"kind": "major_road", "network": "IN:NH", "sort_key": 379, "source": "openstreetmap", "ref": "NH114", "id": 238591811, "highway": "trunk"}}, {"geometry": {"type": "LineString", "coordinates": [[87.79793, 23.46438], [87.79081, 23.47721]]}, "type": "Feature", "properties": {"sort_key": 377, "source": "openstreetmap", "kind": "minor_road", "aeroway": "runway", "id": 64689513}}, {"geometry": {"type": "LineString", "coordinates": [[87.77287, 23.44309], [87.77505, 23.44412], [87.77758, 23.44489], [87.7863, 23.44618], [87.7894, 23.44595], [87.79359, 23.44652], [87.79529, 23.44795], [87.79838, 23.44959], [87.80229, 23.44923], [87.80273, 23.44905]]}, "type": "Feature", "properties": {"sort_key": 376, "source": "openstreetmap", "kind": "major_road", "id": 397152977, "highway": "tertiary"}}, {"geometry": {"type": "LineString", "coordinates": [[87.80273, 23.4794], [87.77419, 23.47958], [87.76955, 23.47902], [87.76473, 23.47809], [87.75879, 23.47796]]}, "type": "Feature", "properties": {"kind": "major_road", "sort_key": 378, "source": "openstreetmap", "ref": "SH14", "id": 22827296, "highway": "primary"}}]}, "earth": {"type": "FeatureCollection", "features": [{"geometry": {"type": "Polygon", "coordinates": [[[87.80273, 23.44309], [87.75879, 23.44309], [87.75879, 23.4834], [87.80273, 23.4834], [87.80273, 23.44309]]]}, "type": "Feature", "properties": {"sort_key": 10, "land": "base", "id": 16383}}]}, "landuse": {"type": "FeatureCollection", "features": []}}