{"boundaries": {"type": "FeatureCollection", "features": []}, "buildings": {"type": "FeatureCollection", "features": []}, "landuse_labels": {"type": "FeatureCollection", "features": []}, "places": {"type": "FeatureCollection", "features": []}, "transit": {"type": "FeatureCollection", "features": []}, "pois": {"type": "FeatureCollection", "features": []}, "water": {"type": "FeatureCollection", "features": []}, "roads": {"type": "FeatureCollection", "features": [{"geometry": {"type": "LineString", "coordinates": [[88.15954, 23.36243], [88.16014, 23.36234], [88.16372, 23.36095], [88.16543, 23.36182], [88.17086, 23.3616], [88.17859, 23.3608], [88.18693, 23.36044], [88.18764, 23.35948], [88.19103, 23.35851], [88.19479, 23.35815], [88.19824, 23.35752]]}, "type": "Feature", "properties": {"sort_key": 376, "source": "openstreetmap", "kind": "major_road", "id": 397172567, "highway": "tertiary"}}]}, "earth": {"type": "FeatureCollection", "features": [{"geometry": {"type": "Polygon", "coordinates": [[[88.19824, 23.32208], [88.1543, 23.32208], [88.1543, 23.36243], [88.19824, 23.36243], [88.19824, 23.32208]]]}, "type": "Feature", "properties": {"sort_key": 10, "land": "base", "id": 16383}}]}, "landuse": {"type": "FeatureCollection", "features": []}}