{"water": {"type": "FeatureCollection", "features": []}, "buildings": {"type": "FeatureCollection", "features": []}, "landuse_labels": {"type": "FeatureCollection", "features": []}, "places": {"type": "FeatureCollection", "features": []}, "transit": {"type": "FeatureCollection", "features": []}, "pois": {"type": "FeatureCollection", "features": []}, "boundaries": {"type": "FeatureCollection", "features": []}, "roads": {"type": "FeatureCollection", "features": [{"geometry": {"type": "MultiLineString", "coordinates": [[[86.91816, 23.684194], [86.920183, 23.683172]], [[86.920183, 23.683172], [86.923112, 23.681746]], [[86.920183, 23.683172], [86.920701, 23.684774]]]}, "type": "Feature", "properties": {"kind": "minor_road", "sort_key": 360, "landuse_kind": "residential", "source": "openstreetmap", "id": 375529001, "highway": "residential"}}, {"geometry": {"type": "LineString", "coordinates": [[86.916399, 23.684208], [86.917489, 23.684482], [86.91816, 23.684194]]}, "type": "Feature", "properties": {"sort_key": 360, "source": "openstreetmap", "kind": "minor_road", "id": 375528999, "highway": "residential"}}, {"geometry": {"type": "LineString", "coordinates": [[86.916307, 23.684774], [86.916399, 23.684208], [86.916358, 23.680327]]}, "type": "Feature", "properties": {"sort_key": 377, "source": "openstreetmap", "kind": "major_road", "id": 327377536, "highway": "secondary"}}]}, "earth": {"type": "FeatureCollection", "features": [{"geometry": {"type": "Polygon", "coordinates": [[[86.923828, 23.664651], [86.901855, 23.664651], [86.901855, 23.684774], [86.923828, 23.684774], [86.923828, 23.664651]]]}, "type": "Feature", "properties": {"sort_key": 10, "land": "base", "id": 16383}}]}, "landuse": {"type": "FeatureCollection", "features": [{"geometry": {"type": "Polygon", "coordinates": [[[86.910308, 23.664651], [86.916776, 23.670021], [86.917708, 23.669691], [86.920314, 23.671829], [86.917795, 23.674095], [86.915784, 23.678677], [86.916139, 23.680317], [86.91704, 23.680334], [86.917313, 23.680476], [86.917494, 23.681134], [86.918941, 23.682259], [86.921347, 23.679844], [86.923828, 23.681838], [86.923828, 23.664651], [86.910308, 23.664651]]]}, "type": "Feature", "properties": {"kind": "industrial", "name": "IISCO Steel Plant", "area": 6795890, "sort_key": 21, "mz_is_building": false, "min_zoom": 9.0, "source": "openstreetmap.org", "id": 64648252}}, {"geometry": {"type": "Polygon", "coordinates": [[[86.923828, 23.681838], [86.921347, 23.679844], [86.918941, 23.682259], [86.917911, 23.683671], [86.918436, 23.684774], [86.923828, 23.684774], [86.923828, 23.681838]]]}, "type": "Feature", "properties": {"kind": "residential", "mz_is_building": false, "sort_key": 20, "area": 1693860, "source": "openstreetmap.org", "min_zoom": 9.0, "id": 375520242}}, {"geometry": {"type": "Polygon", "coordinates": [[[86.917754, 23.680812], [86.918839, 23.681803], [86.920845, 23.679933], [86.919513, 23.678664], [86.919333, 23.678676], [86.91809, 23.67973], [86.918367, 23.680216], [86.917754, 23.680812]]]}, "type": "Feature", "properties": {"kind": "substation", "mz_is_building": false, "sort_key": 65, "area": 67694, "source": "openstreetmap.org", "min_zoom": 9.23263, "id": 396096017}}]}}