{"boundaries": {"type": "FeatureCollection", "features": []}, "buildings": {"type": "FeatureCollection", "features": []}, "landuse_labels": {"type": "FeatureCollection", "features": []}, "places": {"type": "FeatureCollection", "features": []}, "transit": {"type": "FeatureCollection", "features": []}, "pois": {"type": "FeatureCollection", "features": []}, "water": {"type": "FeatureCollection", "features": [{"geometry": {"type": "Polygon", "coordinates": [[[87.363281, 23.716978], [87.364256, 23.716298], [87.36622, 23.714538], [87.369646, 23.709297], [87.373031, 23.705433], [87.373993, 23.704895], [87.365121, 23.704895], [87.363543, 23.706723], [87.363281, 23.707635], [87.363281, 23.716978]]]}, "type": "Feature", "properties": {"sort_key": 200, "source": "openstreetmap.org", "kind": "riverbank", "id": 117962950, "area": 14086100}}, {"geometry": {"type": "LineString", "coordinates": [[87.363281, 23.714912], [87.365927, 23.713123], [87.365468, 23.706733], [87.369194, 23.704895]]}, "type": "Feature", "properties": {"sort_key": 200, "source": "openstreetmap.org", "kind": "river", "name": "Ajay River", "id": 176162293}}, {"geometry": {"type": "LineString", "coordinates": [[87.363281, 23.721194], [87.364689, 23.721724], [87.365141, 23.721736], [87.366521, 23.721299], [87.368314, 23.720338], [87.371088, 23.719536], [87.3715, 23.718989], [87.372443, 23.718454], [87.375045, 23.718649], [87.375483, 23.718272], [87.375881, 23.717214], [87.375802, 23.714176], [87.375549, 23.712839], [87.375702, 23.710887], [87.375383, 23.708618], [87.377086, 23.706327], [87.377646, 23.704895]]}, "type": "Feature", "properties": {"sort_key": 200, "source": "openstreetmap.org", "kind": "river", "id": 319393716}}, {"geometry": {"type": "MultiLineString", "coordinates": [[[87.363281, 23.716978], [87.364256, 23.716297], [87.36622, 23.714538], [87.369646, 23.709297], [87.37303, 23.705432], [87.373993, 23.704895]], [[87.365121, 23.704895], [87.363543, 23.706723], [87.363281, 23.707635]]]}, "type": "Feature", "properties": {"kind": "riverbank", "area": 14086100, "sort_key": 367, "source": "openstreetmap.org", "boundary": "yes", "id": 117962950}}]}, "roads": {"type": "FeatureCollection", "features": []}, "earth": {"type": "FeatureCollection", "features": [{"geometry": {"type": "Polygon", "coordinates": [[[87.385254, 23.704895], [87.363281, 23.704895], [87.363281, 23.725012], [87.385254, 23.725012], [87.385254, 23.704895]]]}, "type": "Feature", "properties": {"sort_key": 10, "land": "base", "id": 16383}}]}, "landuse": {"type": "FeatureCollection", "features": []}}