{"boundaries": {"type": "FeatureCollection", "features": []}, "buildings": {"type": "FeatureCollection", "features": []}, "landuse_labels": {"type": "FeatureCollection", "features": []}, "places": {"type": "FeatureCollection", "features": []}, "transit": {"type": "FeatureCollection", "features": []}, "pois": {"type": "FeatureCollection", "features": [{"geometry": {"type": "Point", "coordinates": [88.329024, 23.242164]}, "type": "Feature", "properties": {"kind_tile_rank": 1, "kind": "station", "min_zoom": 12.0, "id": 1707946190}}]}, "water": {"type": "FeatureCollection", "features": []}, "roads": {"type": "FeatureCollection", "features": [{"geometry": {"type": "LineString", "coordinates": [[88.329712, 23.241346], [88.319247, 23.253627], [88.31651, 23.2574], [88.314692, 23.260661], [88.314327, 23.261534]]}, "type": "Feature", "properties": {"sort_key": 380, "source": "openstreetmap", "kind": "rail", "railway": "rail", "id": 149495513}}, {"geometry": {"type": "LineString", "coordinates": [[88.32904, 23.261534], [88.329476, 23.259529], [88.330078, 23.258394]]}, "type": "Feature", "properties": {"kind": "major_road", "sort_key": 378, "source": "openstreetmap", "ref": "SH6", "id": 327404423, "highway": "primary"}}]}, "earth": {"type": "FeatureCollection", "features": [{"geometry": {"type": "Polygon", "coordinates": [[[88.330078, 23.241346], [88.308105, 23.241346], [88.308105, 23.261534], [88.330078, 23.261534], [88.330078, 23.241346]]]}, "type": "Feature", "properties": {"sort_key": 10, "land": "base", "id": 16383}}]}, "landuse": {"type": "FeatureCollection", "features": []}}