{"boundaries": {"type": "FeatureCollection", "features": []}, "buildings": {"type": "FeatureCollection", "features": []}, "landuse_labels": {"type": "FeatureCollection", "features": []}, "places": {"type": "FeatureCollection", "features": []}, "transit": {"type": "FeatureCollection", "features": []}, "pois": {"type": "FeatureCollection", "features": []}, "water": {"type": "FeatureCollection", "features": [{"geometry": {"type": "Polygon", "coordinates": [[[88.044434, 23.643738], [88.044446, 23.64374], [88.047715, 23.643733], [88.049776, 23.643338], [88.050905, 23.642842], [88.053492, 23.642892], [88.055585, 23.643725], [88.05604, 23.644185], [88.056178, 23.644524], [88.058007, 23.644524], [88.057441, 23.642345], [88.057164, 23.641827], [88.056222, 23.641268], [88.055135, 23.641106], [88.051299, 23.641664], [88.048217, 23.641614], [88.046355, 23.64138], [88.045058, 23.641065], [88.044434, 23.640618], [88.044434, 23.643738]]]}, "type": "Feature", "properties": {"sort_key": 200, "source": "openstreetmap.org", "kind": "riverbank", "id": 326048559, "area": 4493130}}, {"geometry": {"type": "LineString", "coordinates": [[88.044434, 23.641711], [88.046024, 23.642472], [88.048796, 23.642878], [88.053607, 23.642208], [88.055314, 23.642472], [88.057044, 23.643833], [88.057263, 23.644524]]}, "type": "Feature", "properties": {"sort_key": 200, "source": "openstreetmap.org", "kind": "river", "name": "Ajay River", "id": 176166427}}, {"geometry": {"type": "MultiLineString", "coordinates": [[[88.044434, 23.643739], [88.044446, 23.64374], [88.047715, 23.643733], [88.049776, 23.643338], [88.050906, 23.642842], [88.053492, 23.642893], [88.055585, 23.643726], [88.05604, 23.644185], [88.056178, 23.644524]], [[88.058007, 23.644524], [88.057441, 23.642344], [88.057164, 23.641827], [88.056222, 23.641268], [88.055135, 23.641106], [88.051299, 23.641664], [88.048218, 23.641614], [88.046355, 23.64138], [88.045058, 23.641065], [88.044434, 23.640618]]]}, "type": "Feature", "properties": {"kind": "riverbank", "area": 4493130, "sort_key": 367, "source": "openstreetmap.org", "boundary": "yes", "id": 326048559}}]}, "roads": {"type": "FeatureCollection", "features": [{"geometry": {"type": "LineString", "coordinates": [[88.066406, 23.631981], [88.062493, 23.631056], [88.056422, 23.631031], [88.055926, 23.631149], [88.055604, 23.631334], [88.054015, 23.633564], [88.052517, 23.634515], [88.046942, 23.637242], [88.044434, 23.638598]]}, "type": "Feature", "properties": {"sort_key": 376, "source": "openstreetmap", "kind": "major_road", "id": 397152949, "highway": "tertiary"}}]}, "earth": {"type": "FeatureCollection", "features": [{"geometry": {"type": "Polygon", "coordinates": [[[88.066406, 23.624395], [88.044434, 23.624395], [88.044434, 23.644524], [88.066406, 23.644524], [88.066406, 23.624395]]]}, "type": "Feature", "properties": {"sort_key": 10, "land": "base", "id": 16383}}]}, "landuse": {"type": "FeatureCollection", "features": []}}