{"boundaries": {"type": "FeatureCollection", "features": []}, "buildings": {"type": "FeatureCollection", "features": []}, "landuse_labels": {"type": "FeatureCollection", "features": []}, "places": {"type": "FeatureCollection", "features": []}, "transit": {"type": "FeatureCollection", "features": []}, "pois": {"type": "FeatureCollection", "features": []}, "water": {"type": "FeatureCollection", "features": [{"geometry": {"type": "LineString", "coordinates": [[87.431247, 23.80545], [87.431296, 23.805424], [87.431577, 23.805039], [87.431608, 23.804212], [87.431047, 23.803157], [87.430688, 23.801688], [87.430735, 23.801275], [87.431063, 23.800804], [87.43139, 23.80059], [87.431873, 23.800576], [87.434182, 23.801007], [87.435791, 23.800785], [87.436342, 23.800453], [87.437598, 23.79891], [87.438072, 23.798023], [87.438656, 23.797337], [87.439152, 23.797055], [87.440221, 23.796641], [87.44356, 23.795744], [87.447726, 23.796097], [87.448993, 23.795663], [87.450315, 23.793415], [87.451172, 23.7932]]}, "type": "Feature", "properties": {"sort_key": 200, "source": "openstreetmap.org", "kind": "river", "id": 319402161}}]}, "roads": {"type": "FeatureCollection", "features": []}, "earth": {"type": "FeatureCollection", "features": [{"geometry": {"type": "Polygon", "coordinates": [[[87.451172, 23.785345], [87.429199, 23.785345], [87.429199, 23.80545], [87.451172, 23.80545], [87.451172, 23.785345]]]}, "type": "Feature", "properties": {"sort_key": 10, "land": "base", "id": 16383}}]}, "landuse": {"type": "FeatureCollection", "features": []}}