{"water": {"type": "FeatureCollection", "features": []}, "buildings": {"type": "FeatureCollection", "features": []}, "landuse_labels": {"type": "FeatureCollection", "features": []}, "places": {"type": "FeatureCollection", "features": []}, "transit": {"type": "FeatureCollection", "features": []}, "pois": {"type": "FeatureCollection", "features": []}, "boundaries": {"type": "FeatureCollection", "features": []}, "roads": {"type": "FeatureCollection", "features": [{"geometry": {"type": "LineString", "coordinates": [[88.154297, 23.562481], [88.154282, 23.562398], [88.153009, 23.559096], [88.149602, 23.548939], [88.147726, 23.543845]]}, "type": "Feature", "properties": {"kind": "major_road", "sort_key": 378, "source": "openstreetmap", "ref": "SH15", "id": 327864277, "highway": "primary"}}]}, "earth": {"type": "FeatureCollection", "features": [{"geometry": {"type": "Polygon", "coordinates": [[[88.154297, 23.543845], [88.132324, 23.543845], [88.132324, 23.563987], [88.154297, 23.563987], [88.154297, 23.543845]]]}, "type": "Feature", "properties": {"sort_key": 10, "land": "base", "id": 16383}}]}, "landuse": {"type": "FeatureCollection", "features": []}}