{"boundaries": {"type": "FeatureCollection", "features": []}, "buildings": {"type": "FeatureCollection", "features": []}, "landuse_labels": {"type": "FeatureCollection", "features": []}, "places": {"type": "FeatureCollection", "features": []}, "transit": {"type": "FeatureCollection", "features": []}, "pois": {"type": "FeatureCollection", "features": []}, "water": {"type": "FeatureCollection", "features": [{"geometry": {"type": "Polygon", "coordinates": [[[87.3531, 23.71881], [87.3542, 23.72287], [87.36328, 23.71693], [87.36328, 23.70763], [87.36273, 23.70956], [87.35954, 23.71472], [87.35497, 23.7183], [87.3531, 23.71881]]]}, "type": "Feature", "properties": {"sort_key": 200, "source": "openstreetmap.org", "kind": "riverbank", "id": 117962950, "area": 14086100}}, {"geometry": {"type": "Polygon", "coordinates": [[[87.30883, 23.72501], [87.32188, 23.72393], [87.32939, 23.72016], [87.33158, 23.71999], [87.33665, 23.7214], [87.34141, 23.72399], [87.34713, 23.72422], [87.3542, 23.72287], [87.3531, 23.71881], [87.34951, 23.71993], [87.34019, 23.71999], [87.33531, 23.71704], [87.32702, 23.71563], [87.32252, 23.71599], [87.31834, 23.71698], [87.3105, 23.7201], [87.30228, 23.72087], [87.29746, 23.72304], [87.28981, 23.72422], [87.28774, 23.72501], [87.30883, 23.72501]]]}, "type": "Feature", "properties": {"sort_key": 200, "source": "openstreetmap.org", "kind": "riverbank", "id": 117953177, "area": 12415900}}, {"geometry": {"type": "LineString", "coordinates": [[87.30061, 23.72501], [87.31795, 23.71992], [87.33035, 23.71776], [87.34062, 23.72102], [87.35378, 23.72134], [87.36328, 23.71491]]}, "type": "Feature", "properties": {"sort_key": 200, "source": "openstreetmap.org", "kind": "river", "name": "Ajay River", "id": 176162293}}, {"geometry": {"type": "LineString", "coordinates": [[87.35881, 23.72501], [87.35909, 23.72486], [87.36063, 23.72134], [87.36214, 23.72096], [87.36328, 23.72125]]}, "type": "Feature", "properties": {"sort_key": 200, "source": "openstreetmap.org", "kind": "river", "id": 319393716}}, {"geometry": {"type": "MultiLineString", "coordinates": [[[87.3542, 23.72287], [87.35803, 23.7207], [87.36328, 23.71675]], [[87.36328, 23.70763], [87.36273, 23.70956], [87.35954, 23.71472], [87.35497, 23.7183], [87.3531, 23.71881]]]}, "type": "Feature", "properties": {"kind": "riverbank", "area": 14086100, "sort_key": 367, "source": "openstreetmap.org", "boundary": "yes", "id": 117962950}}, {"geometry": {"type": "MultiLineString", "coordinates": [[[87.30883, 23.72501], [87.32188, 23.72393], [87.32939, 23.72016], [87.33158, 23.71999], [87.33665, 23.7214], [87.34141, 23.72399], [87.34713, 23.72422], [87.3542, 23.72287]], [[87.3531, 23.71881], [87.3495, 23.71993], [87.34019, 23.71999], [87.33531, 23.71704], [87.32702, 23.71563], [87.32252, 23.71598], [87.31834, 23.71699], [87.3105, 23.7201], [87.30228, 23.72087], [87.29746, 23.72304], [87.28981, 23.72422], [87.28774, 23.72501]]]}, "type": "Feature", "properties": {"kind": "riverbank", "area": 12415900, "sort_key": 367, "source": "openstreetmap.org", "boundary": "yes", "id": 117953177}}]}, "roads": {"type": "FeatureCollection", "features": [{"geometry": {"type": "MultiLineString", "coordinates": [[[87.27539, 23.70856], [87.27776, 23.71298], [87.28106, 23.72501]], [[87.28122, 23.72501], [87.28018, 23.72137]]]}, "type": "Feature", "properties": {"sort_key": 380, "source": "openstreetmap", "kind": "rail", "railway": "rail", "id": 372680467}}, {"geometry": {"type": "MultiLineString", "coordinates": [[[87.27539, 23.64802], [87.27688, 23.64856], [87.28733, 23.65865], [87.28892, 23.65725], [87.28909, 23.65643], [87.29143, 23.65496], [87.29945, 23.65932], [87.3027, 23.66255], [87.31017, 23.66336], [87.31247, 23.66265], [87.31644, 23.66463], [87.31953, 23.66378], [87.32113, 23.66393], [87.32609, 23.66091], [87.32721, 23.65898], [87.3346, 23.65647]], [[87.27539, 23.71321], [87.2762, 23.71247], [87.27548, 23.70995], [87.2846, 23.70624], [87.28878, 23.71289], [87.29195, 23.7156], [87.29995, 23.71443], [87.30566, 23.71476], [87.32136, 23.70664], [87.32324, 23.7063], [87.3273, 23.70702], [87.33449, 23.70502], [87.35184, 23.70402], [87.35943, 23.70019], [87.36328, 23.69925]]]}, "type": "Feature", "properties": {"sort_key": 377, "source": "openstreetmap", "kind": "major_road", "id": 117962939, "highway": "secondary"}}, {"geometry": {"type": "LineString", "coordinates": [[87.27539, 23.70436], [87.27614, 23.70325], [87.28315, 23.70012], [87.29281, 23.69839]]}, "type": "Feature", "properties": {"kind": "rail", "service": "spur", "sort_key": 361, "source": "openstreetmap", "railway": "rail", "id": 117943143}}, {"geometry": {"type": "LineString", "coordinates": [[87.28733, 23.65865], [87.29092, 23.66376], [87.28845, 23.67627], [87.28394, 23.68594], [87.28002, 23.69289]]}, "type": "Feature", "properties": {"sort_key": 376, "source": "openstreetmap", "kind": "major_road", "id": 117962946, "highway": "tertiary"}}]}, "earth": {"type": "FeatureCollection", "features": [{"geometry": {"type": "Polygon", "coordinates": [[[87.36328, 23.64452], [87.27539, 23.64452], [87.27539, 23.72501], [87.36328, 23.72501], [87.36328, 23.64452]]]}, "type": "Feature", "properties": {"sort_key": 10, "land": "base", "id": 16383}}]}, "landuse": {"type": "FeatureCollection", "features": [{"geometry": {"type": "Polygon", "coordinates": [[[87.30867, 23.66215], [87.30889, 23.66293], [87.31045, 23.66332], [87.31221, 23.66258], [87.31188, 23.66183], [87.31108, 23.6623], [87.30974, 23.66165], [87.30867, 23.66215]]]}, "type": "Feature", "properties": {"kind": "substation", "mz_is_building": false, "sort_key": 65, "area": 46954, "source": "openstreetmap.org", "min_zoom": 9.49652, "id": 118333254}}]}}