{"boundaries": {"type": "FeatureCollection", "features": []}, "buildings": {"type": "FeatureCollection", "features": []}, "landuse_labels": {"type": "FeatureCollection", "features": []}, "places": {"type": "FeatureCollection", "features": []}, "transit": {"type": "FeatureCollection", "features": []}, "pois": {"type": "FeatureCollection", "features": []}, "water": {"type": "FeatureCollection", "features": []}, "roads": {"type": "FeatureCollection", "features": [{"geometry": {"type": "LineString", "coordinates": [[88.1543, 23.26648], [88.15807, 23.26758], [88.15999, 23.26769], [88.16148, 23.26738], [88.16287, 23.26654], [88.16737, 23.26763], [88.16962, 23.26789], [88.175, 23.26661], [88.17915, 23.26671], [88.18107, 23.26647], [88.18351, 23.26738], [88.18673, 23.26719], [88.18813, 23.26817], [88.18955, 23.26818], [88.19002, 23.26881], [88.19076, 23.26893], [88.19224, 23.26848], [88.1953, 23.2686], [88.19608, 23.26946], [88.19824, 23.26994]]}, "type": "Feature", "properties": {"kind": "major_road", "name": "Kalna Rd.", "sort_key": 378, "source": "openstreetmap", "id": 370100797, "highway": "primary"}}, {"geometry": {"type": "LineString", "coordinates": [[88.16858, 23.26783], [88.16865, 23.27203], [88.16916, 23.27235], [88.16931, 23.2728], [88.16927, 23.27341], [88.16889, 23.27364], [88.16918, 23.27547], [88.16971, 23.27648], [88.17055, 23.277], [88.17129, 23.27795], [88.17272, 23.27797], [88.17389, 23.2789], [88.1748, 23.2789], [88.1751, 23.28074], [88.17618, 23.28132], [88.17607, 23.28172]]}, "type": "Feature", "properties": {"sort_key": 376, "source": "openstreetmap", "kind": "major_road", "id": 397172547, "highway": "tertiary"}}]}, "earth": {"type": "FeatureCollection", "features": [{"geometry": {"type": "Polygon", "coordinates": [[[88.19824, 23.24135], [88.1543, 23.24135], [88.1543, 23.28172], [88.19824, 23.28172], [88.19824, 23.24135]]]}, "type": "Feature", "properties": {"sort_key": 10, "land": "base", "id": 16383}}]}, "landuse": {"type": "FeatureCollection", "features": []}}