{"boundaries": {"type": "FeatureCollection", "features": []}, "buildings": {"type": "FeatureCollection", "features": []}, "landuse_labels": {"type": "FeatureCollection", "features": []}, "places": {"type": "FeatureCollection", "features": []}, "transit": {"type": "FeatureCollection", "features": []}, "pois": {"type": "FeatureCollection", "features": []}, "water": {"type": "FeatureCollection", "features": [{"geometry": {"type": "LineString", "coordinates": [[88.3131, 23.32208], [88.31419, 23.31995], [88.3146, 23.3187], [88.31463, 23.31656], [88.31522, 23.31505], [88.31613, 23.31406], [88.31909, 23.31263], [88.32047, 23.31101], [88.32077, 23.309], [88.31999, 23.30752], [88.32015, 23.30668], [88.32061, 23.30623], [88.32227, 23.30621], [88.32433, 23.30762], [88.32907, 23.30893], [88.33008, 23.30889]]}, "type": "Feature", "properties": {"sort_key": 200, "source": "openstreetmap.org", "kind": "river", "id": 374799445}}]}, "roads": {"type": "FeatureCollection", "features": [{"geometry": {"type": "LineString", "coordinates": [[88.31605, 23.31491], [88.31536, 23.31387]]}, "type": "Feature", "properties": {"kind": "major_road", "sort_key": 378, "source": "openstreetmap", "is_bridge": "yes", "ref": "SH6", "id": 240892504, "highway": "primary"}}, {"geometry": {"type": "LineString", "coordinates": [[88.31802, 23.31258], [88.31856, 23.3136]]}, "type": "Feature", "properties": {"kind": "rail", "sort_key": 380, "source": "openstreetmap", "is_bridge": "yes", "railway": "rail", "id": 374799448}}, {"geometry": {"type": "MultiLineString", "coordinates": [[[88.31856, 23.3136], [88.32313, 23.32208]], [[88.31198, 23.28172], [88.31212, 23.30102], [88.31288, 23.30313], [88.31802, 23.31258]]]}, "type": "Feature", "properties": {"sort_key": 380, "source": "openstreetmap", "kind": "rail", "railway": "rail", "id": 374799446}}, {"geometry": {"type": "MultiLineString", "coordinates": [[[88.31536, 23.31387], [88.31024, 23.30626], [88.30918, 23.29564], [88.30941, 23.29442], [88.3101, 23.29343], [88.31285, 23.29226], [88.31336, 23.29149], [88.31337, 23.28524], [88.31389, 23.28172]], [[88.32077, 23.32208], [88.31605, 23.31491]]]}, "type": "Feature", "properties": {"kind": "major_road", "sort_key": 378, "source": "openstreetmap", "ref": "SH6", "id": 173020367, "highway": "primary"}}]}, "earth": {"type": "FeatureCollection", "features": [{"geometry": {"type": "Polygon", "coordinates": [[[88.33008, 23.28172], [88.28613, 23.28172], [88.28613, 23.32208], [88.33008, 23.32208], [88.33008, 23.28172]]]}, "type": "Feature", "properties": {"sort_key": 10, "land": "base", "id": 16383}}]}, "landuse": {"type": "FeatureCollection", "features": []}}