{"boundaries": {"type": "FeatureCollection", "features": []}, "buildings": {"type": "FeatureCollection", "features": []}, "landuse_labels": {"type": "FeatureCollection", "features": []}, "places": {"type": "FeatureCollection", "features": []}, "transit": {"type": "FeatureCollection", "features": []}, "pois": {"type": "FeatureCollection", "features": [{"geometry": {"type": "Point", "coordinates": [88.329894, 23.433095]}, "type": "Feature", "properties": {"kind_tile_rank": 1, "kind": "station", "min_zoom": 12.0, "id": 1766031347}}]}, "water": {"type": "FeatureCollection", "features": [{"geometry": {"type": "Polygon", "coordinates": [[[88.328781, 23.443089], [88.329286, 23.441758], [88.330078, 23.440778], [88.330078, 23.438438], [88.329777, 23.438639], [88.328477, 23.440385], [88.327502, 23.442305], [88.327356, 23.443089], [88.328781, 23.443089]]]}, "type": "Feature", "properties": {"sort_key": 200, "source": "openstreetmap.org", "kind": "water", "id": 326061576, "area": 2805500}}, {"geometry": {"type": "MultiLineString", "coordinates": [[[88.328781, 23.443089], [88.329286, 23.441759], [88.330078, 23.440778]], [[88.330078, 23.438414], [88.329778, 23.438639], [88.329204, 23.439271], [88.328477, 23.440384], [88.327503, 23.442306], [88.327356, 23.443089]]]}, "type": "Feature", "properties": {"kind": "water", "area": 2805500, "sort_key": 367, "source": "openstreetmap.org", "boundary": "yes", "id": 326061576}}]}, "roads": {"type": "FeatureCollection", "features": [{"geometry": {"type": "LineString", "coordinates": [[88.330078, 23.432906], [88.329894, 23.433095], [88.328848, 23.434845], [88.326316, 23.443089]]}, "type": "Feature", "properties": {"sort_key": 380, "source": "openstreetmap", "kind": "rail", "railway": "rail", "id": 374799446}}, {"geometry": {"type": "LineString", "coordinates": [[88.327091, 23.422928], [88.326824, 23.423525], [88.326493, 23.423903], [88.323682, 23.4259], [88.323243, 23.426554], [88.322688, 23.428389], [88.322679, 23.429452], [88.323135, 23.43113], [88.322981, 23.431521], [88.321201, 23.433063], [88.321018, 23.434149], [88.319388, 23.436785], [88.317679, 23.437979], [88.316887, 23.439726], [88.314734, 23.441154], [88.31381, 23.442278], [88.312266, 23.443011], [88.312228, 23.443089]]}, "type": "Feature", "properties": {"kind": "major_road", "sort_key": 378, "source": "openstreetmap", "ref": "SH6", "id": 168540412, "highway": "primary"}}]}, "earth": {"type": "FeatureCollection", "features": [{"geometry": {"type": "Polygon", "coordinates": [[[88.330078, 23.422928], [88.308105, 23.422928], [88.308105, 23.443089], [88.330078, 23.443089], [88.330078, 23.422928]]]}, "type": "Feature", "properties": {"sort_key": 10, "land": "base", "id": 16383}}]}, "landuse": {"type": "FeatureCollection", "features": []}}