{"boundaries": {"type": "FeatureCollection", "features": []}, "buildings": {"type": "FeatureCollection", "features": []}, "landuse_labels": {"type": "FeatureCollection", "features": []}, "places": {"type": "FeatureCollection", "features": []}, "transit": {"type": "FeatureCollection", "features": []}, "pois": {"type": "FeatureCollection", "features": []}, "water": {"type": "FeatureCollection", "features": [{"geometry": {"type": "Polygon", "coordinates": [[[87.714844, 23.619695], [87.715475, 23.619471], [87.717449, 23.617913], [87.719924, 23.614018], [87.72123, 23.612751], [87.722991, 23.609997], [87.723568, 23.60624], [87.723963, 23.605266], [87.724585, 23.604404], [87.724736, 23.604262], [87.721727, 23.604262], [87.720756, 23.606968], [87.717598, 23.61309], [87.714844, 23.614332], [87.714844, 23.619695]]]}, "type": "Feature", "properties": {"kind": "riverbank", "area": 9535990, "sort_key": 200, "source": "openstreetmap.org", "id": -4551842, "osm_relation": true}}, {"geometry": {"type": "LineString", "coordinates": [[87.714844, 23.61682], [87.71778, 23.61413], [87.721027, 23.611446], [87.722874, 23.607303], [87.723418, 23.604262]]}, "type": "Feature", "properties": {"sort_key": 200, "source": "openstreetmap.org", "kind": "river", "name": "Ajay River", "id": 319393715}}, {"geometry": {"type": "MultiLineString", "coordinates": [[[87.714844, 23.619696], [87.715475, 23.619471], [87.717449, 23.617913], [87.719924, 23.614017], [87.72123, 23.612752], [87.722992, 23.609997], [87.723568, 23.60624], [87.723963, 23.605267], [87.724585, 23.604403], [87.724735, 23.604262]], [[87.721727, 23.604262], [87.720757, 23.606967], [87.717598, 23.613089], [87.714844, 23.614332]]]}, "type": "Feature", "properties": {"kind": "riverbank", "area": 9535990, "sort_key": 367, "source": "openstreetmap.org", "boundary": "yes", "id": -4551842}}]}, "roads": {"type": "FeatureCollection", "features": []}, "earth": {"type": "FeatureCollection", "features": [{"geometry": {"type": "Polygon", "coordinates": [[[87.736816, 23.604262], [87.714844, 23.604262], [87.714844, 23.624395], [87.736816, 23.624395], [87.736816, 23.604262]]]}, "type": "Feature", "properties": {"sort_key": 10, "land": "base", "id": 16383}}]}, "landuse": {"type": "FeatureCollection", "features": []}}