{"boundaries": {"type": "FeatureCollection", "features": []}, "buildings": {"type": "FeatureCollection", "features": []}, "landuse_labels": {"type": "FeatureCollection", "features": []}, "places": {"type": "FeatureCollection", "features": []}, "transit": {"type": "FeatureCollection", "features": []}, "pois": {"type": "FeatureCollection", "features": []}, "water": {"type": "FeatureCollection", "features": []}, "roads": {"type": "FeatureCollection", "features": [{"geometry": {"type": "LineString", "coordinates": [[88.066406, 23.516309], [88.065883, 23.516198], [88.062959, 23.516339], [88.062484, 23.516081], [88.062103, 23.515076], [88.061487, 23.514894], [88.055909, 23.515815], [88.053564, 23.515777], [88.050393, 23.516293], [88.049053, 23.51627], [88.04718, 23.5158], [88.044951, 23.516539], [88.044434, 23.516598]]}, "type": "Feature", "properties": {"sort_key": 377, "source": "openstreetmap", "kind": "major_road", "id": 397152946, "highway": "secondary"}}]}, "earth": {"type": "FeatureCollection", "features": [{"geometry": {"type": "Polygon", "coordinates": [[[88.066406, 23.503552], [88.044434, 23.503552], [88.044434, 23.5237], [88.066406, 23.5237], [88.066406, 23.503552]]]}, "type": "Feature", "properties": {"sort_key": 10, "land": "base", "id": 16383}}]}, "landuse": {"type": "FeatureCollection", "features": []}}